pyvelocity/__init__.py
pyvelocity/cli.py
pyvelocity/constants.py
pyvelocity/py.typed
pyvelocity/pyvelocity.py
pyvelocity/checks/__init__.py
pyvelocity/checks/aggregation.py
pyvelocity/checks/badges.py
pyvelocity/checks/classifiers.py
pyvelocity/checks/keywords.py
pyvelocity/checks/legacy_setup_files.py
pyvelocity/checks/line_length.py
pyvelocity/checks/readme.py
pyvelocity/checks/requires_python.py
pyvelocity/checks/typed.py
pyvelocity/checks/using_py_project_toml.py
pyvelocity/checks/zip_safe_false.py
pyvelocity/configurations/__init__.py
pyvelocity/configurations/aggregation.py
pyvelocity/configurations/files/__init__.py
pyvelocity/configurations/files/aggregation.py
pyvelocity/configurations/files/py_project_toml.py
pyvelocity/configurations/files/readme.py
pyvelocity/configurations/files/sections/__init__.py
pyvelocity/configurations/files/sections/black.py
pyvelocity/configurations/files/sections/docformatter.py
pyvelocity/configurations/files/sections/factory.py
pyvelocity/configurations/files/sections/flake8.py
pyvelocity/configurations/files/sections/isort.py
pyvelocity/configurations/files/sections/project.py
pyvelocity/configurations/files/sections/pyvelocity.py
pyvelocity/configurations/files/sections/ruff.py
pyvelocity/configurations/files/sections/setuptools.py
pyvelocity/configurations/files/sections/pylint/__init__.py
pyvelocity/configurations/tools/__init__.py
pyvelocity/configurations/tools/black.py
pyvelocity/configurations/tools/docformatter.py
pyvelocity/configurations/tools/flake8.py
pyvelocity/configurations/tools/isort.py
pyvelocity/configurations/tools/pylint.py
pyvelocity/configurations/tools/pyvelocity.py
pyvelocity/configurations/tools/ruff.py
pyvelocity/regex/__init__.py
pyvelocity/regex/github.py
pyvelocity/regex/markdown.py
pyvelocity/regex/pypi.py
pyvelocity/regex/qlty.py
pyvelocity/regex/shieldsio.py
pyvelocity-0.8.1.dist-info/licenses/LICENSE
pyvelocity-0.8.1.dist-info/METADATA
pyvelocity-0.8.1.dist-info/WHEEL
pyvelocity-0.8.1.dist-info/entry_points.txt
pyvelocity-0.8.1.dist-info/top_level.txt
pyvelocity-0.8.1.dist-info/RECORD
