Metadata-Version: 2.4
Name: pyvelocity
Version: 0.8.1
Summary: Automates task to check configurations about Python project to follow best practices to increase development velocity.
Author-email: Yukihiko Shinoda <yuk.hik.future@gmail.com>
Maintainer-email: Yukihiko Shinoda <yuk.hik.future@gmail.com>
License: MIT License
Project-URL: homepage, https://github.com/yukihiko-shinoda/pyvelocity
Project-URL: repository, https://github.com/yukihiko-shinoda/pyvelocity
Keywords: pyvelocity,pyproject.toml
Classifier: Development Status :: 4 - Beta
Classifier: Intended Audience :: Developers
Classifier: License :: OSI Approved
Classifier: License :: OSI Approved :: MIT License
Classifier: Natural Language :: English
Classifier: Operating System :: OS Independent
Classifier: Topic :: Software Development
Classifier: Topic :: Software Development :: Bug Tracking
Classifier: Topic :: Software Development :: Build Tools
Classifier: Topic :: Software Development :: Quality Assurance
Classifier: Topic :: Software Development :: Testing
Classifier: Topic :: System
Classifier: Topic :: System :: Software Distribution
Classifier: Programming Language :: Python
Classifier: Programming Language :: Python :: 3
Classifier: Programming Language :: Python :: 3.9
Classifier: Programming Language :: Python :: 3.10
Classifier: Programming Language :: Python :: 3.11
Classifier: Programming Language :: Python :: 3.12
Classifier: Programming Language :: Python :: 3.13
Classifier: Typing :: Typed
Requires-Python: >=3.9
License-File: LICENSE
Requires-Dist: click>=7.0
Requires-Dist: packagediscovery>=0.2.0
Requires-Dist: tomli
Requires-Dist: typing-extensions
Provides-Extra: test
Dynamic: license-file
